plyxproto/__init__.py
plyxproto/helpers.py
plyxproto/logicparser.py
plyxproto/model.py
plyxproto/parser.py
plyxproto-3.0.0.dist-info/DESCRIPTION.rst
plyxproto-3.0.0.dist-info/METADATA
plyxproto-3.0.0.dist-info/RECORD
plyxproto-3.0.0.dist-info/WHEEL
plyxproto-3.0.0.dist-info/metadata.json
plyxproto-3.0.0.dist-info/top_level.txt
