Metadata-Version: 2.0
Name: plyxproto
Version: 3.0.0
Summary: xproto parser and processor
Home-page: https://github.com/sb98052/plyprotobuf
Author: Dusan Klinec (original protobuf parser), Sapan Bhatia (xproto extensions)
Author-email: sapan@opennetworking.org
License: Apache Software License
Keywords: xproto protobuf xos parser
Platform: UNKNOWN
Classifier: Development Status :: 5 - Production/Stable
Classifier: Intended Audience :: Developers
Classifier: Topic :: Software Development :: Build Tools
Classifier: License :: OSI Approved :: Apache Software License
Classifier: Programming Language :: Python :: 2
Classifier: Programming Language :: Python :: 2.7
Requires-Dist: ply
